<Properties>
  <MonoDevelop.Ide.Workbench ActiveDocument="Assets/Scripts/Block.cs">
    <Files>
      <File FileName="Assets/Scripts/PlayerController.cs" Line="35" Column="1" />
      <File FileName="Assets/Scripts/Bullet.cs" Line="25" Column="10" />
      <File FileName="Assets/Scripts/Block.cs" Line="40" Column="31" />
      <File FileName="Assets/Scripts/BlockController.cs" Line="5" Column="1" />
    </Files>
    <Pads>
      <Pad Id="ProjectPad">
        <State name="__root__">
          <Node name="GAD_101x_ASM3_FX05543" expanded="True">
            <Node name="Assembly-CSharp" expanded="True">
              <Node name="Assets" expanded="True">
                <Node name="Scripts" expanded="True">
                  <Node name="Block.cs" selected="True" />
                </Node>
              </Node>
            </Node>
          </Node>
        </State>
      </Pad>
    </Pads>
  </MonoDevelop.Ide.Workbench>
  <MonoDevelop.Ide.DebuggingService.PinnedWatches />
  <MonoDevelop.Ide.Workspace ActiveConfiguration="Debug" />
  <MonoDevelop.Ide.ItemProperties.Assembly-CSharp PreferredExecutionTarget="9214a9c6-e33d-4c41-98b1-288b632c3598" />
  <MonoDevelop.Ide.DebuggingService.Breakpoints>
    <BreakpointStore />
  </MonoDevelop.Ide.DebuggingService.Breakpoints>
  <MultiItemStartupConfigurations />
</Properties>